tests/__init__.py
tests/blocks.py
tests/constants.py
tests/models.py
tests/management/__init__.py
tests/management/commands/__init__.py
tests/management/commands/init.py
tests/migrations/0001_initial.py
tests/migrations/__init__.py
wagtailsvg/__init__.py
wagtailsvg/apps.py
wagtailsvg/blocks.py
wagtailsvg/context.py
wagtailsvg/edit_handlers.py
wagtailsvg/models.py
wagtailsvg/views.py
wagtailsvg/wagtail_hooks.py
wagtailsvg/widgets.py
wagtailsvg/migrations/0001_initial.py
wagtailsvg/migrations/0002_svg_edit_code.py
wagtailsvg/migrations/0003_alter_svg_options.py
wagtailsvg/migrations/0004_remove_svg_edit_code.py
wagtailsvg/migrations/0005_alter_svg_file.py
wagtailsvg/migrations/__init__.py
wagtailsvg/static/wagtailsvg/js/chooser-widget.js
wagtailsvg/templates/modeladmin/wagtailsvg/svg/create.html
wagtailsvg/templates/modeladmin/wagtailsvg/svg/edit.html
wagtailsvg/templates/modeladmin/wagtailsvg/svg/index.html
wagtailsvg/templates/wagtailsvg/_results.html
wagtailsvg/templates/wagtailsvg/homepage/site_summary_svg.html
wagtailsvg/templates/wagtailsvg/widgets/chooser.html
wagtailsvg-0.0.37.dist-info/LICENSE
wagtailsvg-0.0.37.dist-info/METADATA
wagtailsvg-0.0.37.dist-info/WHEEL
wagtailsvg-0.0.37.dist-info/top_level.txt
wagtailsvg-0.0.37.dist-info/RECORD
